shubha_banking_api/__init__.py
shubha_banking_api/ps_oop_banking_system.py
shubha_banking_api-0.1.dist-info/License.txt
shubha_banking_api-0.1.dist-info/METADATA
shubha_banking_api-0.1.dist-info/WHEEL
shubha_banking_api-0.1.dist-info/top_level.txt
shubha_banking_api-0.1.dist-info/RECORD
